README.md
setup.cfg
setup.py
packages/caviar/__init__.py
packages/caviar.egg-info/PKG-INFO
packages/caviar.egg-info/SOURCES.txt
packages/caviar.egg-info/dependency_links.txt
packages/caviar.egg-info/namespace_packages.txt
packages/caviar.egg-info/top_level.txt
packages/caviar/domain/__init__.py
packages/caviar/domain/cluster.py
packages/caviar/domain/instance.py
packages/caviar/domain/node.py
packages/caviar/engine/__init__.py
packages/caviar/engine/asadmin.py
packages/caviar/engine/lb.py
packages/caviar/engine/management.py
packages/caviar/engine/nodealloc.py
packages/caviar/network/__init__.py
packages/caviar/network/http.py
packages/caviar/network/ssh.py
packages/caviar/provider/__init__.py
packages/caviar/provider/machinery/__init__.py
packages/caviar/provider/machinery/docker/__init__.py
packages/caviar/provider/machinery/docker/machine.py
packages/caviar/provider/machinery/docker/server.py
packages/caviar/provider/ssh/__init__.py
packages/caviar/provider/ssh/paramiko/__init__.py